src/__init__.py
src/cli.py
src/data_provider.py
src/dual_transport_server.py
src/enhanced_indicators.py
src/main.py
src/mcp_bridge.py
src/talib_registry.py
crypto_powerdata_mcp-0.1.0.dist-info/METADATA
crypto_powerdata_mcp-0.1.0.dist-info/WHEEL
crypto_powerdata_mcp-0.1.0.dist-info/entry_points.txt
crypto_powerdata_mcp-0.1.0.dist-info/licenses/LICENSE
crypto_powerdata_mcp-0.1.0.dist-info/RECORD
